qii/__init__.py
qii/predictor.py
qii/qii.py
qii/qoi.py
qii_tool-0.1.3.dist-info/LICENSE
qii_tool-0.1.3.dist-info/METADATA
qii_tool-0.1.3.dist-info/WHEEL
qii_tool-0.1.3.dist-info/top_level.txt
qii_tool-0.1.3.dist-info/RECORD
