Metadata-Version: 2.1
Name: qii-tool
Version: 0.1.3
Summary: A package implements Quantitative Input Influence method
Home-page: https://github.com/hovinh/QII
Author: Ho Xuan Vinh
Author-email: hxvinh.hcmus@gmail.com
License: UNKNOWN
Platform: UNKNOWN
Classifier: Programming Language :: Python :: 3
Classifier: License :: OSI Approved :: MIT License
Classifier: Operating System :: OS Independent
Requires-Dist: numpy
